sakib_helpers/__init__.py
sakib_helpers/helpers.py
sakib_helpers/app/__init__.py
sakib_helpers/app/admin.py
sakib_helpers/app/apps.py
sakib_helpers/app/models.py
sakib_helpers/app/tests.py
sakib_helpers/app/views.py
sakib_helpers/app/migrations/__init__.py
sakib_helpers/app/templatetags/__init__.py
sakib_helpers/app/templatetags/sakib_helpers.py
sakib_helpers-0.0.3.dist-info/LICENSE
sakib_helpers-0.0.3.dist-info/METADATA
sakib_helpers-0.0.3.dist-info/WHEEL
sakib_helpers-0.0.3.dist-info/top_level.txt
sakib_helpers-0.0.3.dist-info/RECORD
