Metadata-Version: 2.1
Name: sakib-helpers
Version: 0.0.3
Summary: python helper functions/methods
Home-page: https://w3code.tech
Author: Sakib Malik
Author-email: maliksakib347@gmail.com
Project-URL: Docs, https://w3code.tech
Keywords: arithmetic,math,mathematics,python tutorial
Classifier: Development Status :: 1 - Planning
Classifier: Intended Audience :: Developers
Classifier: Programming Language :: Python :: 3
Classifier: Operating System :: Unix
Classifier: Operating System :: MacOS :: MacOS X
Classifier: Operating System :: Microsoft :: Windows
Requires-Python: >=3.6
License-File: LICENSE
Requires-Dist: django (>=3.0)
